ele/__init__.py
ele/element.py
ele/exceptions.py
ele/lib/README.md
ele/lib/elements.json
ele/lib/refs.bib
ele-0.2.0.dist-info/LICENSE.rst
ele-0.2.0.dist-info/METADATA
ele-0.2.0.dist-info/WHEEL
ele-0.2.0.dist-info/top_level.txt
ele-0.2.0.dist-info/RECORD
