Metadata-Version: 2.1
Name: ele
Version: 0.2.0
Summary: A lightweight package with the periodic table of the elements
Home-page: https://github.com/rsdefever/ele
Author: Ryan S. DeFever
Author-email: rdefever@nd.edu
License: MIT
Platform: UNKNOWN
Requires-Python: >=3.6, <4
